setup.py
onlinecsat/__init__.py
onlinecsat/content_filter.py
onlinecsat.egg-info/PKG-INFO
onlinecsat.egg-info/SOURCES.txt
onlinecsat.egg-info/dependency_links.txt
onlinecsat.egg-info/requires.txt
onlinecsat.egg-info/top_level.txt